pygenda/__main__.py
pygenda/pygenda_calendar.py
pygenda/pygenda_config.py
pygenda/pygenda_dialog_entryprops.py
pygenda/pygenda_dialog_event.py
pygenda/pygenda_dialog_find.py
pygenda/pygenda_dialog_import.py
pygenda/pygenda_dialog_todo.py
pygenda/pygenda_entryinfo.py
pygenda/pygenda_gui.py
pygenda/pygenda_util.py
pygenda/pygenda_version.py
pygenda/pygenda_view.py
pygenda/pygenda_view_todo.py
pygenda/pygenda_view_week.py
pygenda/pygenda_view_year.py
pygenda/pygenda_widgets.py
pygenda/app/pygenda.desktop
pygenda/css/T.svg
pygenda/css/cosmo.css
pygenda/css/disc+T.svg
pygenda/css/disc+loop+T.svg
pygenda/css/disc+loop+star+T.svg
pygenda/css/disc+loop+star.svg
pygenda/css/disc+loop.svg
pygenda/css/disc+star+T.svg
pygenda/css/disc+star.svg
pygenda/css/disc.svg
pygenda/css/gemini.css
pygenda/css/loop+T.svg
pygenda/css/loop+star+T.svg
pygenda/css/loop+star.svg
pygenda/css/loop.svg
pygenda/css/pygenda.css
pygenda/css/star+T.svg
pygenda/css/star.svg
pygenda/locale/en_US/LC_MESSAGES/pygenda.mo
pygenda/locale/fr/LC_MESSAGES/pygenda.mo
pygenda/locale/nl/LC_MESSAGES/pygenda.mo
pygenda/ui/dialog_event.ui
pygenda/ui/dialog_find.ui
pygenda/ui/dialog_todo.ui
pygenda/ui/main.ui
pygenda/ui/view_week.ui
pygenda/ui/view_year.ui
pygenda-0.3.8.dist-info/licenses/COPYING
pygenda-0.3.8.dist-info/METADATA
pygenda-0.3.8.dist-info/WHEEL
pygenda-0.3.8.dist-info/top_level.txt
pygenda-0.3.8.dist-info/RECORD
