Metadata-Version: 2.4
Name: pygenda
Version: 0.3.8
Summary: An agenda application inspired by Agenda programs on Psion PDAs.
Author-email: Matthew Lewis <pygenda@semiprime.com>
Project-URL: Homepage, https://github.com/semiprime/pygenda
Project-URL: Homepage (Codeberg), https://codeberg.org/semiprime/pygenda
Keywords: calendar,agenda,todolist,diary,pda,psion,geminipda,cosmocommunicator,linux-mobile
Classifier: Development Status :: 3 - Alpha
Classifier: Environment :: Handhelds/PDA's
Classifier: Environment :: X11 Applications :: GTK
Classifier: License :: OSI Approved :: GNU General Public License v3 (GPLv3)
Classifier: Operating System :: OS Independent
Classifier: Programming Language :: Python :: 3
Classifier: Topic :: Office/Business :: Scheduling
Requires-Python: >=3.5
License-File: COPYING
Requires-Dist: PyGObject
Requires-Dist: python-dateutil
Requires-Dist: icalendar
Requires-Dist: tzlocal!=2.*
Requires-Dist: num2words
Dynamic: license-file
